{ "event_title": " UFC 90: Silva vs Cote ", "total_fights":10, "fights" :[
{"result":"win","fighter_a":"Anderson Silva","fighter_b":"Patrick Cote","knock_downs_fighter_a":"0","knock_downs_fighter_b":"0","significant_strikes_fighter_a":"29","significant_strikes_fighter_b":"16","take_downs_fighter_a":"1","take_downs_fighter_b":"0","submission_attempts_fighter_a":"0","submission_attempts_fighter_b":"0","weight_class":"Middleweight","result_method":"KO/TKO","method_detail":"","total_rounds":"3","end_time":"0:39"},
{"result":"win","fighter_a":"Thiago Alves","fighter_b":"Josh Koscheck","knock_downs_fighter_a":"2","knock_downs_fighter_b":"0","significant_strikes_fighter_a":"80","significant_strikes_fighter_b":"39","take_downs_fighter_a":"0","take_downs_fighter_b":"0","submission_attempts_fighter_a":"0","submission_attempts_fighter_b":"0","weight_class":"Welterweight","result_method":"U-DEC","method_detail":"","total_rounds":"3","end_time":"5:00"},
{"result":"win","fighter_a":"Gray Maynard","fighter_b":"Rich Clementi","knock_downs_fighter_a":"0","knock_downs_fighter_b":"0","significant_strikes_fighter_a":"22","significant_strikes_fighter_b":"7","take_downs_fighter_a":"5","take_downs_fighter_b":"0","submission_attempts_fighter_a":"2","submission_attempts_fighter_b":"0","weight_class":"Lightweight","result_method":"U-DEC","method_detail":"","total_rounds":"3","end_time":"5:00"},
{"result":"win","fighter_a":"Junior Dos Santos","fighter_b":"Fabricio Werdum","knock_downs_fighter_a":"1","knock_downs_fighter_b":"0","significant_strikes_fighter_a":"7","significant_strikes_fighter_b":"6","take_downs_fighter_a":"0","take_downs_fighter_b":"0","submission_attempts_fighter_a":"0","submission_attempts_fighter_b":"0","weight_class":"Heavyweight","result_method":"KO/TKO","method_detail":"1","total_rounds":"1","end_time":"1:21"},
{"result":"win","fighter_a":"Sean Sherk","fighter_b":"Tyson Griffin","knock_downs_fighter_a":"0","knock_downs_fighter_b":"0","significant_strikes_fighter_a":"92","significant_strikes_fighter_b":"74","take_downs_fighter_a":"3","take_downs_fighter_b":"0","submission_attempts_fighter_a":"0","submission_attempts_fighter_b":"0","weight_class":"Lightweight","result_method":"U-DEC","method_detail":"","total_rounds":"3","end_time":"5:00"},
{"result":"win","fighter_a":"Thales Leites","fighter_b":"Drew McFedries","knock_downs_fighter_a":"0","knock_downs_fighter_b":"0","significant_strikes_fighter_a":"0","significant_strikes_fighter_b":"1","take_downs_fighter_a":"1","take_downs_fighter_b":"0","submission_attempts_fighter_a":"1","submission_attempts_fighter_b":"0","weight_class":"Middleweight","result_method":"SUB","method_detail":"1","total_rounds":"1","end_time":"1:18"},
{"result":"win","fighter_a":"Spencer Fisher","fighter_b":"Shannon Gugerty","knock_downs_fighter_a":"1","knock_downs_fighter_b":"0","significant_strikes_fighter_a":"30","significant_strikes_fighter_b":"28","take_downs_fighter_a":"0","take_downs_fighter_b":"2","submission_attempts_fighter_a":"2","submission_attempts_fighter_b":"1","weight_class":"Lightweight","result_method":"SUB","method_detail":"3","total_rounds":"3","end_time":"3:56"},
{"result":"win","fighter_a":"Dan Miller","fighter_b":"Matt Horwich","knock_downs_fighter_a":"0","knock_downs_fighter_b":"0","significant_strikes_fighter_a":"31","significant_strikes_fighter_b":"15","take_downs_fighter_a":"6","take_downs_fighter_b":"0","submission_attempts_fighter_a":"0","submission_attempts_fighter_b":"5","weight_class":"Middleweight","result_method":"U-DEC","method_detail":"","total_rounds":"3","end_time":"5:00"},
{"result":"win","fighter_a":"Hermes Franca","fighter_b":"Marcus Aurelio","knock_downs_fighter_a":"0","knock_downs_fighter_b":"0","significant_strikes_fighter_a":"60","significant_strikes_fighter_b":"40","take_downs_fighter_a":"0","take_downs_fighter_b":"1","submission_attempts_fighter_a":"0","submission_attempts_fighter_b":"0","weight_class":"Lightweight","result_method":"U-DEC","method_detail":"","total_rounds":"3","end_time":"5:00"},
{"result":"win","fighter_a":"Pete Sell","fighter_b":"Joshua Burkman","knock_downs_fighter_a":"0","knock_downs_fighter_b":"0","significant_strikes_fighter_a":"65","significant_strikes_fighter_b":"50","take_downs_fighter_a":"1","take_downs_fighter_b":"4","submission_attempts_fighter_a":"1","submission_attempts_fighter_b":"0","weight_class":"Welterweight","result_method":"U-DEC","method_detail":"","total_rounds":"3","end_time":"5:00"}
] 
}