{ "event_title": " UFC 125: Resolution ", "total_fights":11, "fights" :[
{"result":"draw","fighter_a":"draw","fighter_b":"Frankie Edgar","knock_downs_fighter_a":"Gray Maynard","knock_downs_fighter_b":"0","significant_strikes_fighter_a":"3","significant_strikes_fighter_b":"95","take_downs_fighter_a":"71","take_downs_fighter_b":"3","submission_attempts_fighter_a":"3","submission_attempts_fighter_b":"2","weight_class":"1","result_method":"Lightweight","method_detail":"5","total_rounds":"5","end_time":"5:00"},
{"result":"win","fighter_a":"Brian Stann","fighter_b":"Chris Leben","knock_downs_fighter_a":"3","knock_downs_fighter_b":"0","significant_strikes_fighter_a":"30","significant_strikes_fighter_b":"7","take_downs_fighter_a":"0","take_downs_fighter_b":"0","submission_attempts_fighter_a":"1","submission_attempts_fighter_b":"0","weight_class":"Middleweight","result_method":"KO/TKO","method_detail":"1","total_rounds":"1","end_time":"3:37"},
{"result":"nc","fighter_a":"nc","fighter_b":"Brandon Vera","knock_downs_fighter_a":"Thiago Silva","knock_downs_fighter_b":"0","significant_strikes_fighter_a":"0","significant_strikes_fighter_b":"19","take_downs_fighter_a":"51","take_downs_fighter_b":"0","submission_attempts_fighter_a":"3","submission_attempts_fighter_b":"0","weight_class":"1","result_method":"Light Heavyweight","method_detail":"3","total_rounds":"3","end_time":"5:00"},
{"result":"win","fighter_a":"Dong Hyun Kim","fighter_b":"Nate Diaz","knock_downs_fighter_a":"0","knock_downs_fighter_b":"0","significant_strikes_fighter_a":"19","significant_strikes_fighter_b":"36","take_downs_fighter_a":"3","take_downs_fighter_b":"1","submission_attempts_fighter_a":"0","submission_attempts_fighter_b":"1","weight_class":"Welterweight","result_method":"U-DEC","method_detail":"","total_rounds":"3","end_time":"5:00"},
{"result":"win","fighter_a":"Clay Guida","fighter_b":"Takanori Gomi","knock_downs_fighter_a":"0","knock_downs_fighter_b":"0","significant_strikes_fighter_a":"12","significant_strikes_fighter_b":"14","take_downs_fighter_a":"3","take_downs_fighter_b":"0","submission_attempts_fighter_a":"2","submission_attempts_fighter_b":"0","weight_class":"Lightweight","result_method":"SUB","method_detail":"2","total_rounds":"2","end_time":"4:27"},
{"result":"win","fighter_a":"Jeremy Stephens","fighter_b":"Marcus Davis","knock_downs_fighter_a":"1","knock_downs_fighter_b":"0","significant_strikes_fighter_a":"25","significant_strikes_fighter_b":"17","take_downs_fighter_a":"0","take_downs_fighter_b":"2","submission_attempts_fighter_a":"2","submission_attempts_fighter_b":"0","weight_class":"Lightweight","result_method":"KO/TKO","method_detail":"3","total_rounds":"3","end_time":"2:33"},
{"result":"win","fighter_a":"Dustin Poirier","fighter_b":"Josh Grispi","knock_downs_fighter_a":"0","knock_downs_fighter_b":"0","significant_strikes_fighter_a":"77","significant_strikes_fighter_b":"16","take_downs_fighter_a":"0","take_downs_fighter_b":"2","submission_attempts_fighter_a":"0","submission_attempts_fighter_b":"2","weight_class":"Featherweight","result_method":"U-DEC","method_detail":"","total_rounds":"3","end_time":"5:00"},
{"result":"win","fighter_a":"Brad Tavares","fighter_b":"Phil Baroni","knock_downs_fighter_a":"1","knock_downs_fighter_b":"1","significant_strikes_fighter_a":"22","significant_strikes_fighter_b":"11","take_downs_fighter_a":"0","take_downs_fighter_b":"0","submission_attempts_fighter_a":"0","submission_attempts_fighter_b":"1","weight_class":"Middleweight","result_method":"KO/TKO","method_detail":"1","total_rounds":"1","end_time":"4:20"},
{"result":"win","fighter_a":"Diego Nunes","fighter_b":"Mike Brown","knock_downs_fighter_a":"0","knock_downs_fighter_b":"0","significant_strikes_fighter_a":"65","significant_strikes_fighter_b":"68","take_downs_fighter_a":"0","take_downs_fighter_b":"4","submission_attempts_fighter_a":"0","submission_attempts_fighter_b":"0","weight_class":"Featherweight","result_method":"S-DEC","method_detail":"","total_rounds":"3","end_time":"5:00"},
{"result":"win","fighter_a":"Daniel Roberts","fighter_b":"Greg Soto","knock_downs_fighter_a":"0","knock_downs_fighter_b":"0","significant_strikes_fighter_a":"3","significant_strikes_fighter_b":"6","take_downs_fighter_a":"1","take_downs_fighter_b":"0","submission_attempts_fighter_a":"2","submission_attempts_fighter_b":"1","weight_class":"Welterweight","result_method":"SUB","method_detail":"1","total_rounds":"1","end_time":"3:45"},
{"result":"win","fighter_a":"Jacob Volkmann","fighter_b":"Antonio McKee","knock_downs_fighter_a":"0","knock_downs_fighter_b":"0","significant_strikes_fighter_a":"10","significant_strikes_fighter_b":"25","take_downs_fighter_a":"1","take_downs_fighter_b":"1","submission_attempts_fighter_a":"2","submission_attempts_fighter_b":"0","weight_class":"Lightweight","result_method":"S-DEC","method_detail":"","total_rounds":"3","end_time":"5:00"}
] 
}