{ "event_title": " UFC 72: Victory ", "total_fights":8, "fights" :[
{"result":"win","fighter_a":"Rich Franklin","fighter_b":"Yushin Okami","knock_downs_fighter_a":"0","knock_downs_fighter_b":"0","significant_strikes_fighter_a":"36","significant_strikes_fighter_b":"17","take_downs_fighter_a":"1","take_downs_fighter_b":"1","submission_attempts_fighter_a":"0","submission_attempts_fighter_b":"3","weight_class":"Middleweight","result_method":"U-DEC","method_detail":"","total_rounds":"3","end_time":"5:00"},
{"result":"win","fighter_a":"Forrest Griffin","fighter_b":"Hector Ramirez","knock_downs_fighter_a":"0","knock_downs_fighter_b":"0","significant_strikes_fighter_a":"113","significant_strikes_fighter_b":"20","take_downs_fighter_a":"0","take_downs_fighter_b":"2","submission_attempts_fighter_a":"0","submission_attempts_fighter_b":"0","weight_class":"Light Heavyweight","result_method":"U-DEC","method_detail":"","total_rounds":"3","end_time":"5:00"},
{"result":"win","fighter_a":"Jason MacDonald","fighter_b":"Rory Singer","knock_downs_fighter_a":"0","knock_downs_fighter_b":"0","significant_strikes_fighter_a":"30","significant_strikes_fighter_b":"17","take_downs_fighter_a":"2","take_downs_fighter_b":"1","submission_attempts_fighter_a":"0","submission_attempts_fighter_b":"1","weight_class":"Middleweight","result_method":"KO/TKO","method_detail":"2","total_rounds":"2","end_time":"3:18"},
{"result":"win","fighter_a":"Tyson Griffin","fighter_b":"Clay Guida","knock_downs_fighter_a":"0","knock_downs_fighter_b":"0","significant_strikes_fighter_a":"50","significant_strikes_fighter_b":"36","take_downs_fighter_a":"2","take_downs_fighter_b":"4","submission_attempts_fighter_a":"2","submission_attempts_fighter_b":"2","weight_class":"Lightweight","result_method":"S-DEC","method_detail":"","total_rounds":"3","end_time":"5:00"},
{"result":"win","fighter_a":"Ed Herman","fighter_b":"Scott Smith","knock_downs_fighter_a":"0","knock_downs_fighter_b":"0","significant_strikes_fighter_a":"24","significant_strikes_fighter_b":"3","take_downs_fighter_a":"3","take_downs_fighter_b":"0","submission_attempts_fighter_a":"2","submission_attempts_fighter_b":"2","weight_class":"Middleweight","result_method":"SUB","method_detail":"2","total_rounds":"2","end_time":"2:25"},
{"result":"win","fighter_a":"Marcus Davis","fighter_b":"Jason Tan","knock_downs_fighter_a":"1","knock_downs_fighter_b":"0","significant_strikes_fighter_a":"9","significant_strikes_fighter_b":"6","take_downs_fighter_a":"0","take_downs_fighter_b":"0","submission_attempts_fighter_a":"0","submission_attempts_fighter_b":"0","weight_class":"Welterweight","result_method":"KO/TKO","method_detail":"1","total_rounds":"1","end_time":"1:15"},
{"result":"win","fighter_a":"Eddie Sanchez","fighter_b":"Colin Robinson","knock_downs_fighter_a":"0","knock_downs_fighter_b":"0","significant_strikes_fighter_a":"41","significant_strikes_fighter_b":"36","take_downs_fighter_a":"1","take_downs_fighter_b":"1","submission_attempts_fighter_a":"0","submission_attempts_fighter_b":"2","weight_class":"Heavyweight","result_method":"KO/TKO","method_detail":"2","total_rounds":"2","end_time":"0:32"},
{"result":"win","fighter_a":"Dustin Hazelett","fighter_b":"Stevie Lynch","knock_downs_fighter_a":"0","knock_downs_fighter_b":"0","significant_strikes_fighter_a":"20","significant_strikes_fighter_b":"7","take_downs_fighter_a":"0","take_downs_fighter_b":"0","submission_attempts_fighter_a":"1","submission_attempts_fighter_b":"0","weight_class":"Welterweight","result_method":"SUB","method_detail":"1","total_rounds":"1","end_time":"2:50"}
] 
}