{ "event_title": " UFC Fight Night: Henderson vs Masvidal ", "total_fights":11, "fights" :[
{"result":"win","fighter_a":"Benson Henderson","fighter_b":"Jorge Masvidal","knock_downs_fighter_a":"0","knock_downs_fighter_b":"0","significant_strikes_fighter_a":"86","significant_strikes_fighter_b":"77","take_downs_fighter_a":"3","take_downs_fighter_b":"1","submission_attempts_fighter_a":"0","submission_attempts_fighter_b":"1","weight_class":"Welterweight","result_method":"S-DEC","method_detail":"","total_rounds":"5","end_time":"5:00"},
{"result":"win","fighter_a":"Dong Hyun Kim","fighter_b":"Dominic Waters","knock_downs_fighter_a":"0","knock_downs_fighter_b":"0","significant_strikes_fighter_a":"6","significant_strikes_fighter_b":"0","take_downs_fighter_a":"1","take_downs_fighter_b":"0","submission_attempts_fighter_a":"0","submission_attempts_fighter_b":"0","weight_class":"Welterweight","result_method":"KO/TKO","method_detail":"1","total_rounds":"1","end_time":"3:11"},
{"result":"win","fighter_a":"Alberto Mina","fighter_b":"Yoshihiro Akiyama","knock_downs_fighter_a":"1","knock_downs_fighter_b":"0","significant_strikes_fighter_a":"69","significant_strikes_fighter_b":"78","take_downs_fighter_a":"2","take_downs_fighter_b":"0","submission_attempts_fighter_a":"0","submission_attempts_fighter_b":"0","weight_class":"Welterweight","result_method":"S-DEC","method_detail":"","total_rounds":"3","end_time":"5:00"},
{"result":"win","fighter_a":"Dooho Choi","fighter_b":"Sam Sicilia","knock_downs_fighter_a":"1","knock_downs_fighter_b":"0","significant_strikes_fighter_a":"18","significant_strikes_fighter_b":"8","take_downs_fighter_a":"0","take_downs_fighter_b":"0","submission_attempts_fighter_a":"0","submission_attempts_fighter_b":"0","weight_class":"Featherweight","result_method":"KO/TKO","method_detail":"1","total_rounds":"1","end_time":"1:33"},
{"result":"win","fighter_a":"Dongi Yang","fighter_b":"Jake Collier","knock_downs_fighter_a":"0","knock_downs_fighter_b":"1","significant_strikes_fighter_a":"29","significant_strikes_fighter_b":"22","take_downs_fighter_a":"1","take_downs_fighter_b":"0","submission_attempts_fighter_a":"0","submission_attempts_fighter_b":"0","weight_class":"Middleweight","result_method":"KO/TKO","method_detail":"2","total_rounds":"2","end_time":"1:50"},
{"result":"win","fighter_a":"Mike de la Torre","fighter_b":"Yui Chul Nam","knock_downs_fighter_a":"0","knock_downs_fighter_b":"0","significant_strikes_fighter_a":"47","significant_strikes_fighter_b":"53","take_downs_fighter_a":"0","take_downs_fighter_b":"1","submission_attempts_fighter_a":"0","submission_attempts_fighter_b":"0","weight_class":"Featherweight","result_method":"S-DEC","method_detail":"","total_rounds":"3","end_time":"5:00"},
{"result":"win","fighter_a":"Tae Hyun Bang","fighter_b":"Leo Kuntz","knock_downs_fighter_a":"1","knock_downs_fighter_b":"0","significant_strikes_fighter_a":"54","significant_strikes_fighter_b":"31","take_downs_fighter_a":"1","take_downs_fighter_b":"3","submission_attempts_fighter_a":"2","submission_attempts_fighter_b":"1","weight_class":"Lightweight","result_method":"S-DEC","method_detail":"","total_rounds":"3","end_time":"5:00"},
{"result":"win","fighter_a":"Seo Hee Ham","fighter_b":"Cortney Casey","knock_downs_fighter_a":"0","knock_downs_fighter_b":"0","significant_strikes_fighter_a":"71","significant_strikes_fighter_b":"78","take_downs_fighter_a":"0","take_downs_fighter_b":"0","submission_attempts_fighter_a":"0","submission_attempts_fighter_b":"0","weight_class":"Women's Strawweight","result_method":"U-DEC","method_detail":"","total_rounds":"3","end_time":"5:00"},
{"result":"win","fighter_a":"Fredy Serrano","fighter_b":"Yao Zhikui","knock_downs_fighter_a":"0","knock_downs_fighter_b":"0","significant_strikes_fighter_a":"3","significant_strikes_fighter_b":"1","take_downs_fighter_a":"1","take_downs_fighter_b":"0","submission_attempts_fighter_a":"0","submission_attempts_fighter_b":"0","weight_class":"Flyweight","result_method":"KO/TKO","method_detail":"","total_rounds":"1","end_time":"0:44"},
{"result":"win","fighter_a":"Marco Beltran","fighter_b":"Guangyou Ning","knock_downs_fighter_a":"0","knock_downs_fighter_b":"0","significant_strikes_fighter_a":"30","significant_strikes_fighter_b":"23","take_downs_fighter_a":"1","take_downs_fighter_b":"0","submission_attempts_fighter_a":"0","submission_attempts_fighter_b":"0","weight_class":"Bantamweight","result_method":"S-DEC","method_detail":"","total_rounds":"3","end_time":"5:00"},
{"result":"win","fighter_a":"Dominique Steele","fighter_b":"Dong Hyun Ma","knock_downs_fighter_a":"1","knock_downs_fighter_b":"0","significant_strikes_fighter_a":"36","significant_strikes_fighter_b":"19","take_downs_fighter_a":"4","take_downs_fighter_b":"0","submission_attempts_fighter_a":"0","submission_attempts_fighter_b":"0","weight_class":"Welterweight","result_method":"KO/TKO","method_detail":"3","total_rounds":"3","end_time":"0:27"}
] 
}