{ "event_title": " UFC on FOX: Holm vs. Shevchenko ", "total_fights":11, "fights" :[
{"result":"win","fighter_a":"Valentina Shevchenko","fighter_b":"Holly Holm","knock_downs_fighter_a":"0","knock_downs_fighter_b":"0","significant_strikes_fighter_a":"87","significant_strikes_fighter_b":"54","take_downs_fighter_a":"3","take_downs_fighter_b":"0","submission_attempts_fighter_a":"0","submission_attempts_fighter_b":"0","weight_class":"Women's Bantamweight","result_method":"U-DEC","method_detail":"","total_rounds":"5","end_time":"5:00"},
{"result":"win","fighter_a":"Edson Barboza","fighter_b":"Gilbert Melendez","knock_downs_fighter_a":"0","knock_downs_fighter_b":"0","significant_strikes_fighter_a":"56","significant_strikes_fighter_b":"39","take_downs_fighter_a":"1","take_downs_fighter_b":"0","submission_attempts_fighter_a":"0","submission_attempts_fighter_b":"0","weight_class":"Lightweight","result_method":"U-DEC","method_detail":"","total_rounds":"3","end_time":"5:00"},
{"result":"win","fighter_a":"Francis Ngannou","fighter_b":"Bojan Mihajlovic","knock_downs_fighter_a":"0","knock_downs_fighter_b":"0","significant_strikes_fighter_a":"8","significant_strikes_fighter_b":"3","take_downs_fighter_a":"0","take_downs_fighter_b":"0","submission_attempts_fighter_a":"0","submission_attempts_fighter_b":"0","weight_class":"Heavyweight","result_method":"KO/TKO","method_detail":"1","total_rounds":"1","end_time":"1:34"},
{"result":"win","fighter_a":"Felice Herrig","fighter_b":"Kailin Curran","knock_downs_fighter_a":"0","knock_downs_fighter_b":"0","significant_strikes_fighter_a":"13","significant_strikes_fighter_b":"5","take_downs_fighter_a":"1","take_downs_fighter_b":"0","submission_attempts_fighter_a":"1","submission_attempts_fighter_b":"0","weight_class":"Women's Strawweight","result_method":"SUB","method_detail":"1","total_rounds":"1","end_time":"1:59"},
{"result":"win","fighter_a":"Eddie Wineland","fighter_b":"Frankie Saenz","knock_downs_fighter_a":"1","knock_downs_fighter_b":"0","significant_strikes_fighter_a":"42","significant_strikes_fighter_b":"45","take_downs_fighter_a":"0","take_downs_fighter_b":"1","submission_attempts_fighter_a":"0","submission_attempts_fighter_b":"0","weight_class":"Bantamweight","result_method":"KO/TKO","method_detail":"3","total_rounds":"3","end_time":"1:54"},
{"result":"win","fighter_a":"Darren Elkins","fighter_b":"Godofredo Pepey","knock_downs_fighter_a":"0","knock_downs_fighter_b":"0","significant_strikes_fighter_a":"33","significant_strikes_fighter_b":"20","take_downs_fighter_a":"5","take_downs_fighter_b":"0","submission_attempts_fighter_a":"0","submission_attempts_fighter_b":"2","weight_class":"Featherweight","result_method":"U-DEC","method_detail":"","total_rounds":"3","end_time":"5:00"},
{"result":"win","fighter_a":"Kamaru Usman","fighter_b":"Alexander Yakovlev","knock_downs_fighter_a":"0","knock_downs_fighter_b":"0","significant_strikes_fighter_a":"41","significant_strikes_fighter_b":"8","take_downs_fighter_a":"5","take_downs_fighter_b":"0","submission_attempts_fighter_a":"0","submission_attempts_fighter_b":"0","weight_class":"Welterweight","result_method":"U-DEC","method_detail":"","total_rounds":"3","end_time":"5:00"},
{"result":"win","fighter_a":"Michel Prazeres","fighter_b":"JC Cottrell","knock_downs_fighter_a":"0","knock_downs_fighter_b":"0","significant_strikes_fighter_a":"48","significant_strikes_fighter_b":"14","take_downs_fighter_a":"7","take_downs_fighter_b":"0","submission_attempts_fighter_a":"1","submission_attempts_fighter_b":"0","weight_class":"Lightweight","result_method":"U-DEC","method_detail":"","total_rounds":"3","end_time":"5:00"},
{"result":"win","fighter_a":"Alex Oliveira","fighter_b":"James Moontasri","knock_downs_fighter_a":"0","knock_downs_fighter_b":"0","significant_strikes_fighter_a":"58","significant_strikes_fighter_b":"12","take_downs_fighter_a":"2","take_downs_fighter_b":"0","submission_attempts_fighter_a":"0","submission_attempts_fighter_b":"0","weight_class":"Welterweight","result_method":"U-DEC","method_detail":"","total_rounds":"3","end_time":"5:00"},
{"result":"win","fighter_a":"Jason Knight","fighter_b":"Jim Alers","knock_downs_fighter_a":"0","knock_downs_fighter_b":"0","significant_strikes_fighter_a":"76","significant_strikes_fighter_b":"41","take_downs_fighter_a":"1","take_downs_fighter_b":"4","submission_attempts_fighter_a":"0","submission_attempts_fighter_b":"0","weight_class":"Featherweight","result_method":"S-DEC","method_detail":"","total_rounds":"3","end_time":"5:00"},
{"result":"win","fighter_a":"Luis Henrique","fighter_b":"Dmitrii Smoliakov","knock_downs_fighter_a":"0","knock_downs_fighter_b":"0","significant_strikes_fighter_a":"20","significant_strikes_fighter_b":"14","take_downs_fighter_a":"1","take_downs_fighter_b":"0","submission_attempts_fighter_a":"1","submission_attempts_fighter_b":"0","weight_class":"Heavyweight","result_method":"SUB","method_detail":"2","total_rounds":"2","end_time":"3:58"}
] 
}