{ "event_title": " UFC Fight Night: Miocic vs Maldonado ", "total_fights":12, "fights" :[
{"result":"win","fighter_a":"Stipe Miocic","fighter_b":"Fabio Maldonado","knock_downs_fighter_a":"1","knock_downs_fighter_b":"0","significant_strikes_fighter_a":"8","significant_strikes_fighter_b":"2","take_downs_fighter_a":"0","take_downs_fighter_b":"0","submission_attempts_fighter_a":"0","submission_attempts_fighter_b":"0","weight_class":"Heavyweight","result_method":"KO/TKO","method_detail":"1","total_rounds":"1","end_time":"0:35"},
{"result":"win","fighter_a":"Antonio Carlos Junior","fighter_b":"Vitor Miranda","knock_downs_fighter_a":"0","knock_downs_fighter_b":"0","significant_strikes_fighter_a":"19","significant_strikes_fighter_b":"21","take_downs_fighter_a":"5","take_downs_fighter_b":"0","submission_attempts_fighter_a":"1","submission_attempts_fighter_b":"0","weight_class":"Heavyweight","result_method":"U-DEC","method_detail":"","total_rounds":"3","end_time":"5:00"},
{"result":"win","fighter_a":"Warlley Alves","fighter_b":"Marcio Alexandre Junior","knock_downs_fighter_a":"1","knock_downs_fighter_b":"0","significant_strikes_fighter_a":"19","significant_strikes_fighter_b":"8","take_downs_fighter_a":"2","take_downs_fighter_b":"0","submission_attempts_fighter_a":"1","submission_attempts_fighter_b":"0","weight_class":"Middleweight","result_method":"SUB","method_detail":"3","total_rounds":"3","end_time":"0:25"},
{"result":"win","fighter_a":"Demian Maia","fighter_b":"Alexander Yakovlev","knock_downs_fighter_a":"1","knock_downs_fighter_b":"0","significant_strikes_fighter_a":"29","significant_strikes_fighter_b":"22","take_downs_fighter_a":"2","take_downs_fighter_b":"1","submission_attempts_fighter_a":"0","submission_attempts_fighter_b":"0","weight_class":"Welterweight","result_method":"U-DEC","method_detail":"","total_rounds":"3","end_time":"5:00"},
{"result":"win","fighter_a":"Robert Peralta","fighter_b":"Rony Jason","knock_downs_fighter_a":"0","knock_downs_fighter_b":"0","significant_strikes_fighter_a":"51","significant_strikes_fighter_b":"30","take_downs_fighter_a":"1","take_downs_fighter_b":"2","submission_attempts_fighter_a":"0","submission_attempts_fighter_b":"1","weight_class":"Featherweight","result_method":"S-DEC","method_detail":"","total_rounds":"3","end_time":"5:00"},
{"result":"win","fighter_a":"Rashid Magomedov","fighter_b":"Rodrigo Damm","knock_downs_fighter_a":"1","knock_downs_fighter_b":"0","significant_strikes_fighter_a":"63","significant_strikes_fighter_b":"37","take_downs_fighter_a":"0","take_downs_fighter_b":"0","submission_attempts_fighter_a":"0","submission_attempts_fighter_b":"0","weight_class":"Lightweight","result_method":"U-DEC","method_detail":"","total_rounds":"3","end_time":"5:00"},
{"result":"win","fighter_a":"Elias Silverio","fighter_b":"Ernest Chavez","knock_downs_fighter_a":"0","knock_downs_fighter_b":"0","significant_strikes_fighter_a":"65","significant_strikes_fighter_b":"54","take_downs_fighter_a":"1","take_downs_fighter_b":"0","submission_attempts_fighter_a":"1","submission_attempts_fighter_b":"0","weight_class":"Lightweight","result_method":"SUB","method_detail":"3","total_rounds":"3","end_time":"4:21"},
{"result":"win","fighter_a":"Gasan Umalatov","fighter_b":"Paulo Thiago","knock_downs_fighter_a":"0","knock_downs_fighter_b":"0","significant_strikes_fighter_a":"24","significant_strikes_fighter_b":"42","take_downs_fighter_a":"1","take_downs_fighter_b":"1","submission_attempts_fighter_a":"0","submission_attempts_fighter_b":"0","weight_class":"Welterweight","result_method":"U-DEC","method_detail":"","total_rounds":"3","end_time":"5:00"},
{"result":"win","fighter_a":"Edimilson Souza","fighter_b":"Mark Eddiva","knock_downs_fighter_a":"0","knock_downs_fighter_b":"0","significant_strikes_fighter_a":"79","significant_strikes_fighter_b":"54","take_downs_fighter_a":"0","take_downs_fighter_b":"0","submission_attempts_fighter_a":"0","submission_attempts_fighter_b":"0","weight_class":"Featherweight","result_method":"KO/TKO","method_detail":"2","total_rounds":"2","end_time":"4:52"},
{"result":"win","fighter_a":"Ricardo Abreu","fighter_b":"Wagner Silva","knock_downs_fighter_a":"2","knock_downs_fighter_b":"0","significant_strikes_fighter_a":"33","significant_strikes_fighter_b":"17","take_downs_fighter_a":"0","take_downs_fighter_b":"0","submission_attempts_fighter_a":"1","submission_attempts_fighter_b":"0","weight_class":"Middleweight","result_method":"SUB","method_detail":"2","total_rounds":"2","end_time":"1:06"},
{"result":"win","fighter_a":"Marcos Rogerio de Lima","fighter_b":"Richardson Moreira","knock_downs_fighter_a":"1","knock_downs_fighter_b":"0","significant_strikes_fighter_a":"7","significant_strikes_fighter_b":"3","take_downs_fighter_a":"0","take_downs_fighter_b":"0","submission_attempts_fighter_a":"0","submission_attempts_fighter_b":"0","weight_class":"Heavyweight","result_method":"KO/TKO","method_detail":"1","total_rounds":"1","end_time":"0:20"},
{"result":"win","fighter_a":"Pedro Munhoz","fighter_b":"Matt Hobar","knock_downs_fighter_a":"0","knock_downs_fighter_b":"0","significant_strikes_fighter_a":"24","significant_strikes_fighter_b":"7","take_downs_fighter_a":"2","take_downs_fighter_b":"0","submission_attempts_fighter_a":"1","submission_attempts_fighter_b":"0","weight_class":"Bantamweight","result_method":"KO/TKO","method_detail":"1","total_rounds":"1","end_time":"2:47"}
] 
}