{ "event_title": " UFC Fight Night 2 ", "total_fights":7, "fights" :[
{"result":"win","fighter_a":"David Loiseau","fighter_b":"Evan Tanner","knock_downs_fighter_a":"0","knock_downs_fighter_b":"0","significant_strikes_fighter_a":"13","significant_strikes_fighter_b":"15","take_downs_fighter_a":"0","take_downs_fighter_b":"3","submission_attempts_fighter_a":"0","submission_attempts_fighter_b":"2","weight_class":"Middleweight","result_method":"KO/TKO","method_detail":"","total_rounds":"2","end_time":"4:15"},
{"result":"win","fighter_a":"Chris Leben","fighter_b":"Edwin DeWees","knock_downs_fighter_a":"0","knock_downs_fighter_b":"0","significant_strikes_fighter_a":"5","significant_strikes_fighter_b":"5","take_downs_fighter_a":"0","take_downs_fighter_b":"1","submission_attempts_fighter_a":"1","submission_attempts_fighter_b":"2","weight_class":"Middleweight","result_method":"SUB","method_detail":"1","total_rounds":"1","end_time":"3:26"},
{"result":"win","fighter_a":"Brandon Vera","fighter_b":"Fabiano Scherner","knock_downs_fighter_a":"2","knock_downs_fighter_b":"0","significant_strikes_fighter_a":"28","significant_strikes_fighter_b":"10","take_downs_fighter_a":"0","take_downs_fighter_b":"1","submission_attempts_fighter_a":"0","submission_attempts_fighter_b":"0","weight_class":"Heavyweight","result_method":"KO/TKO","method_detail":"2","total_rounds":"2","end_time":"3:22"},
{"result":"win","fighter_a":"Drew Fickett","fighter_b":"Josh Koscheck","knock_downs_fighter_a":"1","knock_downs_fighter_b":"0","significant_strikes_fighter_a":"5","significant_strikes_fighter_b":"8","take_downs_fighter_a":"0","take_downs_fighter_b":"6","submission_attempts_fighter_a":"3","submission_attempts_fighter_b":"0","weight_class":"Welterweight","result_method":"SUB","method_detail":"3","total_rounds":"3","end_time":"4:28"},
{"result":"win","fighter_a":"Spencer Fisher","fighter_b":"Thiago Alves","knock_downs_fighter_a":"0","knock_downs_fighter_b":"0","significant_strikes_fighter_a":"13","significant_strikes_fighter_b":"19","take_downs_fighter_a":"1","take_downs_fighter_b":"3","submission_attempts_fighter_a":"3","submission_attempts_fighter_b":"0","weight_class":"Welterweight","result_method":"SUB","method_detail":"2","total_rounds":"2","end_time":"4:43"},
{"result":"win","fighter_a":"Jon Fitch","fighter_b":"Brock Larson","knock_downs_fighter_a":"0","knock_downs_fighter_b":"0","significant_strikes_fighter_a":"25","significant_strikes_fighter_b":"14","take_downs_fighter_a":"5","take_downs_fighter_b":"1","submission_attempts_fighter_a":"2","submission_attempts_fighter_b":"3","weight_class":"Middleweight","result_method":"U-DEC","method_detail":"","total_rounds":"3","end_time":"5:00"},
{"result":"win","fighter_a":"Jonathan Goulet","fighter_b":"Jay Hieron","knock_downs_fighter_a":"0","knock_downs_fighter_b":"0","significant_strikes_fighter_a":"14","significant_strikes_fighter_b":"10","take_downs_fighter_a":"0","take_downs_fighter_b":"9","submission_attempts_fighter_a":"1","submission_attempts_fighter_b":"3","weight_class":"Welterweight","result_method":"KO/TKO","method_detail":"","total_rounds":"3","end_time":"1:05"}
] 
}