{ "event_title": " UFC Fight Night: Dern vs. Rodriguez ", "total_fights":9, "fights" :[
{"result":"win","fighter_a":"Marina Rodriguez","fighter_b":"Mackenzie Dern","knock_downs_fighter_a":"0","knock_downs_fighter_b":"0","significant_strikes_fighter_a":"144","significant_strikes_fighter_b":"49","take_downs_fighter_a":"0","take_downs_fighter_b":"1","submission_attempts_fighter_a":"1","submission_attempts_fighter_b":"1","weight_class":"Women's Strawweight","result_method":"U-DEC","method_detail":"","total_rounds":"5","end_time":"5:00"},
{"result":"win","fighter_a":"Randy Brown","fighter_b":"Jared Gooden","knock_downs_fighter_a":"0","knock_downs_fighter_b":"0","significant_strikes_fighter_a":"115","significant_strikes_fighter_b":"81","take_downs_fighter_a":"0","take_downs_fighter_b":"0","submission_attempts_fighter_a":"0","submission_attempts_fighter_b":"0","weight_class":"Welterweight","result_method":"U-DEC","method_detail":"","total_rounds":"3","end_time":"5:00"},
{"result":"win","fighter_a":"Matheus Nicolau","fighter_b":"Tim Elliott","knock_downs_fighter_a":"0","knock_downs_fighter_b":"0","significant_strikes_fighter_a":"64","significant_strikes_fighter_b":"70","take_downs_fighter_a":"1","take_downs_fighter_b":"1","submission_attempts_fighter_a":"0","submission_attempts_fighter_b":"0","weight_class":"Flyweight","result_method":"U-DEC","method_detail":"","total_rounds":"3","end_time":"5:00"},
{"result":"win","fighter_a":"Mariya Agapova","fighter_b":"Sabina Mazo","knock_downs_fighter_a":"1","knock_downs_fighter_b":"0","significant_strikes_fighter_a":"93","significant_strikes_fighter_b":"62","take_downs_fighter_a":"0","take_downs_fighter_b":"0","submission_attempts_fighter_a":"1","submission_attempts_fighter_b":"0","weight_class":"Women's Flyweight","result_method":"SUB","method_detail":"3","total_rounds":"3","end_time":"0:53"},
{"result":"win","fighter_a":"Chris Gutierrez","fighter_b":"Felipe Colares","knock_downs_fighter_a":"0","knock_downs_fighter_b":"0","significant_strikes_fighter_a":"96","significant_strikes_fighter_b":"41","take_downs_fighter_a":"0","take_downs_fighter_b":"1","submission_attempts_fighter_a":"0","submission_attempts_fighter_b":"0","weight_class":"Bantamweight","result_method":"S-DEC","method_detail":"","total_rounds":"3","end_time":"5:00"},
{"result":"win","fighter_a":"Alexandr Romanov","fighter_b":"Jared Vanderaa","knock_downs_fighter_a":"0","knock_downs_fighter_b":"0","significant_strikes_fighter_a":"56","significant_strikes_fighter_b":"13","take_downs_fighter_a":"5","take_downs_fighter_b":"0","submission_attempts_fighter_a":"0","submission_attempts_fighter_b":"0","weight_class":"Heavyweight","result_method":"KO/TKO","method_detail":"2","total_rounds":"2","end_time":"4:43"},
{"result":"win","fighter_a":"Damon Jackson","fighter_b":"Charles Rosa","knock_downs_fighter_a":"0","knock_downs_fighter_b":"0","significant_strikes_fighter_a":"41","significant_strikes_fighter_b":"34","take_downs_fighter_a":"6","take_downs_fighter_b":"2","submission_attempts_fighter_a":"2","submission_attempts_fighter_b":"0","weight_class":"Featherweight","result_method":"U-DEC","method_detail":"","total_rounds":"3","end_time":"5:00"},
{"result":"win","fighter_a":"Loopy Godinez","fighter_b":"Silvana Gomez Juarez","knock_downs_fighter_a":"0","knock_downs_fighter_b":"0","significant_strikes_fighter_a":"11","significant_strikes_fighter_b":"3","take_downs_fighter_a":"5","take_downs_fighter_b":"0","submission_attempts_fighter_a":"1","submission_attempts_fighter_b":"0","weight_class":"Women's Strawweight","result_method":"SUB","method_detail":"1","total_rounds":"1","end_time":"4:14"},
{"result":"win","fighter_a":"Steve Garcia","fighter_b":"Charlie Ontiveros","knock_downs_fighter_a":"0","knock_downs_fighter_b":"2","significant_strikes_fighter_a":"34","significant_strikes_fighter_b":"7","take_downs_fighter_a":"3","take_downs_fighter_b":"0","submission_attempts_fighter_a":"0","submission_attempts_fighter_b":"0","weight_class":"Lightweight","result_method":"KO/TKO","method_detail":"2","total_rounds":"2","end_time":"1:51"}
] 
}